{
    "timestamp": "2026-07-22 09:27:48",
    "stage_index": 31,
    "stage": "chunk_input_ready",
    "provider": "gemma",
    "model": "google/gemma-4-31B-it",
    "source_pdf": "data/input/CrimePunishment-EPUB2.pdf",
    "processed_pdf": "data/input/CrimePunishment-EPUB2.pdf",
    "chunk": "15",
    "total_chunks": 40,
    "start_page": 191,
    "end_page": 204,
    "input_chars": 27921,
    "input_chunk_file": "data/output/input_chunks/CrimePunishment-EPUB2_gemma_20260722_092702/chunk_15_pages_191-204.json"
}