{
    "timestamp": "2026-07-07 18:31:11",
    "stage": "before_gemma_toc_generation",
    "provider": "gemma",
    "model": "google/gemma-4-31B-it",
    "source_pdf": "data/input/부교재3.PDF",
    "processed_pdf": "/tmp/ai_gemma_ascii_pdfs/3.pdf",
    "chunk": "18.3",
    "total_chunks": 19,
    "start_page": 557,
    "end_page": 557,
    "input_chars": 3636,
    "text": "[PAGE 557]\n[L s=8.0 r=0.84 x=512 y=53 b=0 i=0 f=f8] 찾아보기∙xiii\n[L s=9.5 r=1.00 x=65 y=86 b=0 i=0 f=f7] 외부 대조군 188 원인모형 63 위험-혜택 비 210\n[L s=9.5 r=1.00 x=65 y=101 b=0 i=0 f=f7] 외부노출 1256 원자력발전소 573, 580 윈슬로우 21, 39\n[L s=9.5 r=1.00 x=65 y=116 b=0 i=0 f=f7] 외부요인 61 원직장 복귀율 1274 윌슨 5\n[L s=9.5 r=1.00 x=65 y=131 b=0 i=0 f=f7] 외부효과 904, 1190 원진레이온 772, 835 유기염소계 713\n[L s=9.5 r=1.00 x=65 y=146 b=0 i=0 f=f7] 외삽 604 원헬스 384, 430 유기용제 689, 880\n[L s=9.5 r=1.00 x=65 y=162 b=0 i=0 f=f7] 외상성 스트레스 1179 월경성 환경오염 724 유기인계 711\n[L s=9.5 r=1.00 x=65 y=177 b=0 i=0 f=f7] 외인성 물질 262 웨브 38 유도기간 64\n[L s=9.5 r=1.00 x=65 y=192 b=0 i=0 f=f7] 외적타당도 149, 222 웰니스 모형 16 유럽종양학회 1201\n[L s=9.5 r=1.00 x=65 y=207 b=0 i=0 f=f7] 요검사 1227 웰컴 트러스트 1388 유리섬유 583, 641, 642\n[L s=9.5 r=1.00 x=65 y=222 b=0 i=0 f=f7] 요로감염 448 위계적 APC 성장곡선 모형 202 유방암 477\n[L s=9.5 r=1.00 x=65 y=237 b=0 i=0 f=f7] 요로결석 529 위기 소통의 원칙 1330 유방암검진 1215\n[L s=9.5 r=1.00 x=65 y=253 b=0 i=0 f=f7] 요세포검사 1228 위기경보 1328 유병 환자 99, 183\n[L s=9.5 r=1.00 x=65 y=268 b=0 i=0 f=f7] 요실금 530 위기경보 수준 1347 유병교차비 184, 296\n[L s=9.5 r=1.00 x=65 y=283 b=0 i=0 f=f7] 요약 316 위기소통 1330 유병률 98, 183\n[L s=9.5 r=1.00 x=65 y=298 b=0 i=0 f=f7] 요약 및 지침 318 위생 571 유병률 연구 183\n[L s=9.5 r=1.00 x=65 y=313 b=0 i=0 f=f7] 요약추정치 301 위생경찰 43 유병률비 184, 296\n[L s=9.5 r=1.00 x=65 y=329 b=0 i=0 f=f7] 요양급여 824, 1073, 1277 위생학 34 유사노출근로자 집단 1253\n[L s=9.5 r=1.00 x=65 y=344 b=0 i=0 f=f7] 요양급여비용 1055 위암 473 유사한 연관성 66\n[L s=9.5 r=1.00 x=65 y=359 b=0 i=0 f=f7] 요양기관 당연지정제 920, 1070 위암검진 1213 유소견율 1281\n[L s=9.5 r=1.00 x=65 y=374 b=0 i=0 f=f7] 요인 노출률 184 위약효과 212 유아기 139\n[L s=9.5 r=1.00 x=65 y=389 b=0 i=0 f=f7] 요인 노출-질병의 연속선 260 위양성 264, 331, 1209, 1213 유엔개발계획 1352\n[L s=9.5 r=1.00 x=65 y=404 b=0 i=0 f=f7] 요인설계 211 위양성률 152 유엔식량농업기구 251\n[L s=9.5 r=1.00 x=65 y=420 b=0 i=0 f=f7] 욕구 1002 위염 514 유엔아동기금 1352\n[L s=9.5 r=1.00 x=65 y=435 b=0 i=0 f=f7] 용량-반응 평가 603 위음성 1209, 1213 유엔인구활동기금 1352\n[L s=9.5 r=1.00 x=65 y=450 b=0 i=0 f=f7] 용량-반응관계 596 위음성률 152 유엔환경계획 40, 1352\n[L s=9.5 r=1.00 x=65 y=465 b=0 i=0 f=f7] 용접 흄 641, 643 위해 602 유연휘발유 572, 574, 672\n[L s=9.5 r=1.00 x=65 y=480 b=0 i=0 f=f7] 용접공폐증 853 위해 요인설계 217 유의수준 280\n[L s=9.5 r=1.00 x=65 y=496 b=0 i=0 f=f7] 용존산소 751, 753 위해도 결정 606 유의확률 280\n[L s=9.5 r=1.00 x=65 y=511 b=0 i=0 f=f7] 우도비 343 위해도 관리 606, 611 유전력 199\n[L s=9.5 r=1.00 x=65 y=526 b=0 i=0 f=f7] 우두국 42 위해사건 1024, 1025 유전력연구 266\n[L s=9.5 r=1.00 x=65 y=541 b=0 i=0 f=f7] 우두백신 1190 위해성평가 611 유전성 형태 267\n[L s=9.5 r=1.00 x=65 y=556 b=0 i=0 f=f7] 우선순위 결정 1105 위해소통 607 유전역학 263, 264\n[L s=9.5 r=1.00 x=65 y=571 b=0 i=0 f=f7] 우성 유전요인 199 위험 210 유전자 간 상호작용 199\n[L s=9.5 r=1.00 x=65 y=587 b=0 i=0 f=f7] 우울증 872, 1217 위험 고르기 1045 유전자 기능 확인 연구 267\n[L s=9.5 r=1.00 x=65 y=602 b=0 i=0 f=f7] 우울증 선별검사 1217 위험 예측 264 유전자 다형성 260\n[L s=9.5 r=1.00 x=65 y=617 b=0 i=0 f=f7] 우울증 유병률 1217 위험 평가 264, 1329 유전자분리분석 266\n[L s=9.5 r=1.00 x=65 y=632 b=0 i=0 f=f7] 우주방사선 1239 위험기간 207 유전자의 위치 266\n[L s=9.5 r=1.00 x=65 y=647 b=0 i=0 f=f7] 우주비행 646 위험도 94, 193 유전자재조합식품 762\n[L s=9.5 r=1.00 x=65 y=662 b=0 i=0 f=f7] 우주선 660 위험도 평가 262 유전자형 261\n[L s=9.5 r=1.00 x=65 y=678 b=0 i=0 f=f7] 우편 조사 74 위험물안전관리법 615 유전적 변이 261\n[L s=9.5 r=1.00 x=65 y=693 b=0 i=0 f=f7] 운동강도 1177 위험성 확인 603 유전체 249, 261, 273, 621\n[L s=9.5 r=1.00 x=65 y=708 b=0 i=0 f=f7] 운동처방 1177 위험소통 1330 유전체데이터 1317\n[L s=9.5 r=1.00 x=65 y=723 b=0 i=0 f=f7] 웁살라모니터링센터 243 위험요인 62 유전체역학 263, 264\n[L s=9.5 r=1.00 x=65 y=738 b=0 i=0 f=f7] 원내감염 446 위험음주자 1169 유전체전장연관성연구 265, 268\n[L s=9.5 r=1.00 x=65 y=754 b=0 i=0 f=f7] 원내폐렴 448 위험의 공간 129 유전체전장연구 268\n[L s=9.5 r=1.00 x=65 y=769 b=0 i=0 f=f7] 원발성 비만 1181 위험-이익 비 217 유전체학 1317\n[L s=9.5 r=1.00 x=65 y=784 b=0 i=0 f=f7] 원인기준 6 위험한 행동 1029 유전-환경 상호작용 593"
}